{
  "id": "16_phone_internet_2",
  "title": "Phone & internet (Part 2)",
  "emoji": "📱",
  "language": "English",
  "items": [
    {
      "id": "16_phone_internet_text",
      "type": "word",
      "text": "text",
      "practiceType": "chooseTranslation"
    },
    {
      "id": "16_phone_internet_message",
      "type": "word",
      "text": "message",
      "practiceType": "chooseTranslation"
    },
    {
      "id": "16_phone_internet_password",
      "type": "word",
      "text": "password",
      "practiceType": "chooseTranslation"
    },
    {
      "id": "16_phone_internet_internet",
      "type": "word",
      "text": "internet",
      "practiceType": "chooseTranslation"
    },
    {
      "id": "16_phone_internet_online",
      "type": "word",
      "text": "online",
      "practiceType": "chooseTranslation"
    },
    {
      "id": "16_phone_internet_do_you_have_internet",
      "type": "sentence",
      "text": "Do you have internet?",
      "practiceType": "formulateSentense"
    },
    {
      "id": "16_phone_internet_what_is_your_email",
      "type": "sentence",
      "text": "What is your email?",
      "practiceType": "formulateSentense"
    },
    {
      "id": "16_phone_internet_i_am_online",
      "type": "sentence",
      "text": "I am online.",
      "practiceType": "formulateSentense"
    },
    {
      "id": "16_phone_internet_can_you_send_me_a_message",
      "type": "sentence",
      "text": "Can you send me a message?",
      "practiceType": "formulateSentense"
    },
    {
      "id": "16_phone_internet_the_wifi_is_slow",
      "type": "sentence",
      "text": "The wifi is slow.",
      "practiceType": "formulateSentense"
    }
  ]
}