{
  "id": "32_time_and_dates_1",
  "title": "tempo e date (Part 1)",
  "emoji": "🕐",
  "language": "Italian",
  "items": [
    {
      "id": "32_time_and_dates_time",
      "type": "word",
      "text": "tempo",
      "practiceType": "chooseTranslation"
    },
    {
      "id": "32_time_and_dates_date",
      "type": "word",
      "text": "data",
      "practiceType": "chooseTranslation"
    },
    {
      "id": "32_time_and_dates_hour",
      "type": "word",
      "text": "ora",
      "practiceType": "chooseTranslation"
    },
    {
      "id": "32_time_and_dates_minute",
      "type": "word",
      "text": "minuto",
      "practiceType": "chooseTranslation"
    },
    {
      "id": "32_time_and_dates_second",
      "type": "word",
      "text": "secondo",
      "practiceType": "chooseTranslation"
    },
    {
      "id": "32_time_and_dates_what_time_is_it",
      "type": "sentence",
      "text": "Che ore sono?",
      "practiceType": "formulateSentense"
    },
    {
      "id": "32_time_and_dates_what_date_is_it_today",
      "type": "sentence",
      "text": "Che data è oggi?",
      "practiceType": "formulateSentense"
    },
    {
      "id": "32_time_and_dates_it_is_three_oclock",
      "type": "sentence",
      "text": "Sono le tre.",
      "practiceType": "formulateSentense"
    },
    {
      "id": "32_time_and_dates_today_is_monday",
      "type": "sentence",
      "text": "Oggi è lunedì.",
      "practiceType": "formulateSentense"
    },
    {
      "id": "32_time_and_dates_what_day_is_tomorrow",
      "type": "sentence",
      "text": "Che giorno è domani?",
      "practiceType": "formulateSentense"
    }
  ]
}