{
  "id": "24_family_and_relationships_2",
  "title": "Gia đình và mối quan hệ (Part 2)",
  "emoji": "👨‍👩‍👧‍👦",
  "language": "Vietnamese",
  "items": [
    {
      "id": "24_family_and_relationships_friend",
      "type": "word",
      "text": "bạn",
      "practiceType": "chooseTranslation"
    },
    {
      "id": "24_family_and_relationships_husband",
      "type": "word",
      "text": "chồng",
      "practiceType": "chooseTranslation"
    },
    {
      "id": "24_family_and_relationships_wife",
      "type": "word",
      "text": "vợ",
      "practiceType": "chooseTranslation"
    },
    {
      "id": "24_family_and_relationships_child",
      "type": "word",
      "text": "trẻ em",
      "practiceType": "chooseTranslation"
    },
    {
      "id": "24_family_and_relationships_parent",
      "type": "word",
      "text": "cha mẹ",
      "practiceType": "chooseTranslation"
    },
    {
      "id": "24_family_and_relationships_we_are_good_friends",
      "type": "sentence",
      "text": "Chúng tôi là bạn tốt.",
      "practiceType": "formulateSentense"
    },
    {
      "id": "24_family_and_relationships_my_husband_likes_cooking",
      "type": "sentence",
      "text": "Chồng tôi thích nấu ăn.",
      "practiceType": "formulateSentense"
    },
    {
      "id": "24_family_and_relationships_do_you_have_children",
      "type": "sentence",
      "text": "Bạn có con không?",
      "practiceType": "formulateSentense"
    },
    {
      "id": "24_family_and_relationships_my_parents_live_in_the_city",
      "type": "sentence",
      "text": "Cha mẹ tôi sống ở thành phố.",
      "practiceType": "formulateSentense"
    },
    {
      "id": "24_family_and_relationships_i_love_my_family_very_much",
      "type": "sentence",
      "text": "Tôi yêu gia đình tôi rất nhiều.",
      "practiceType": "formulateSentense"
    }
  ]
}