{
  "id": "26_health_and_medical_1",
  "title": "Zdraví a lékařství (Part 1)",
  "emoji": "🏥",
  "language": "Czech",
  "items": [
    {
      "id": "26_health_and_medical_health",
      "type": "word",
      "text": "zdraví",
      "practiceType": "chooseTranslation"
    },
    {
      "id": "26_health_and_medical_doctor",
      "type": "word",
      "text": "doktor",
      "practiceType": "chooseTranslation"
    },
    {
      "id": "26_health_and_medical_hospital",
      "type": "word",
      "text": "nemocnice",
      "practiceType": "chooseTranslation"
    },
    {
      "id": "26_health_and_medical_medicine",
      "type": "word",
      "text": "lék",
      "practiceType": "chooseTranslation"
    },
    {
      "id": "26_health_and_medical_pain",
      "type": "word",
      "text": "bolest",
      "practiceType": "chooseTranslation"
    },
    {
      "id": "26_health_and_medical_how_are_you_feeling_today",
      "type": "sentence",
      "text": "Jak se cítíte dnes?",
      "practiceType": "formulateSentense"
    },
    {
      "id": "26_health_and_medical_i_need_to_see_a_doctor",
      "type": "sentence",
      "text": "Potřebuji vidět doktora.",
      "practiceType": "formulateSentense"
    },
    {
      "id": "26_health_and_medical_where_is_the_nearest_hospital",
      "type": "sentence",
      "text": "Kde je nejbližší nemocnice?",
      "practiceType": "formulateSentense"
    },
    {
      "id": "26_health_and_medical_i_have_a_headache",
      "type": "sentence",
      "text": "Bolí mě hlava.",
      "practiceType": "formulateSentense"
    },
    {
      "id": "26_health_and_medical_can_i_make_an_appointment",
      "type": "sentence",
      "text": "Můžu si domluvit schůzku?",
      "practiceType": "formulateSentense"
    }
  ]
}