{
  "id": "01_essentials",
  "title": "begroetingen en beleefdheid",
  "emoji": "👋",
  "language": "Dutch",
  "items": [
    {
      "id": "01_essentials_hello",
      "type": "word",
      "text": "hallo",
      "practiceType": "chooseTranslation"
    },
    {
      "id": "01_essentials_hi",
      "type": "word",
      "text": "hallo",
      "practiceType": "chooseTranslation"
    },
    {
      "id": "01_essentials_please",
      "type": "word",
      "text": "alsjeblieft",
      "practiceType": "chooseTranslation"
    },
    {
      "id": "01_essentials_thank_you",
      "type": "word",
      "text": "dank je",
      "practiceType": "chooseTranslation"
    },
    {
      "id": "01_essentials_thanks",
      "type": "word",
      "text": "dank je",
      "practiceType": "chooseTranslation"
    },
    {
      "id": "01_essentials_yes",
      "type": "word",
      "text": "ja",
      "practiceType": "chooseTranslation"
    },
    {
      "id": "01_essentials_no",
      "type": "word",
      "text": "nee",
      "practiceType": "chooseTranslation"
    },
    {
      "id": "01_essentials_goodbye",
      "type": "word",
      "text": "tot ziens",
      "practiceType": "chooseTranslation"
    },
    {
      "id": "01_essentials_welcome",
      "type": "word",
      "text": "welkom",
      "practiceType": "chooseTranslation"
    },
    {
      "id": "01_essentials_okay",
      "type": "word",
      "text": "oké",
      "practiceType": "chooseTranslation"
    },
    {
      "id": "01_essentials_excuse_me",
      "type": "sentence",
      "text": "Excuseer.",
      "practiceType": "formulateSentense"
    },
    {
      "id": "01_essentials_sorry",
      "type": "sentence",
      "text": "Sorry.",
      "practiceType": "formulateSentense"
    },
    {
      "id": "01_essentials_good_morning",
      "type": "sentence",
      "text": "Goedemorgen.",
      "practiceType": "formulateSentense"
    },
    {
      "id": "01_essentials_good_evening",
      "type": "sentence",
      "text": "Goedenavond.",
      "practiceType": "formulateSentense"
    },
    {
      "id": "01_essentials_good_night",
      "type": "sentence",
      "text": "Goedenacht.",
      "practiceType": "formulateSentense"
    },
    {
      "id": "01_essentials_see_you_later",
      "type": "sentence",
      "text": "Tot later.",
      "practiceType": "formulateSentense"
    },
    {
      "id": "01_essentials_have_a_nice_day",
      "type": "sentence",
      "text": "Fijne dag.",
      "practiceType": "formulateSentense"
    },
    {
      "id": "01_essentials_you_are_welcome",
      "type": "sentence",
      "text": "Graag gedaan.",
      "practiceType": "formulateSentense"
    },
    {
      "id": "01_essentials_no_problem",
      "type": "sentence",
      "text": "Geen probleem.",
      "practiceType": "formulateSentense"
    },
    {
      "id": "01_essentials_take_care",
      "type": "sentence",
      "text": "Zorg goed voor jezelf.",
      "practiceType": "formulateSentense"
    }
  ]
}