{
  "id": "04_numbers_time_basics",
  "title": "Числа та основи часу",
  "emoji": "🔢",
  "language": "Ukrainian",
  "items": [
    {
      "id": "04_numbers_time_basics_zero",
      "type": "word",
      "text": "нуль",
      "practiceType": "chooseTranslation"
    },
    {
      "id": "04_numbers_time_basics_one",
      "type": "word",
      "text": "один",
      "practiceType": "chooseTranslation"
    },
    {
      "id": "04_numbers_time_basics_two",
      "type": "word",
      "text": "два",
      "practiceType": "chooseTranslation"
    },
    {
      "id": "04_numbers_time_basics_three",
      "type": "word",
      "text": "три",
      "practiceType": "chooseTranslation"
    },
    {
      "id": "04_numbers_time_basics_four",
      "type": "word",
      "text": "чотири",
      "practiceType": "chooseTranslation"
    },
    {
      "id": "04_numbers_time_basics_five",
      "type": "word",
      "text": "п'ять",
      "practiceType": "chooseTranslation"
    },
    {
      "id": "04_numbers_time_basics_six",
      "type": "word",
      "text": "шість",
      "practiceType": "chooseTranslation"
    },
    {
      "id": "04_numbers_time_basics_seven",
      "type": "word",
      "text": "сім",
      "practiceType": "chooseTranslation"
    },
    {
      "id": "04_numbers_time_basics_eight",
      "type": "word",
      "text": "вісім",
      "practiceType": "chooseTranslation"
    },
    {
      "id": "04_numbers_time_basics_nine",
      "type": "word",
      "text": "дев'ять",
      "practiceType": "chooseTranslation"
    },
    {
      "id": "04_numbers_time_basics_ten",
      "type": "word",
      "text": "десять",
      "practiceType": "chooseTranslation"
    },
    {
      "id": "04_numbers_time_basics_twenty",
      "type": "word",
      "text": "двадцять",
      "practiceType": "chooseTranslation"
    },
    {
      "id": "04_numbers_time_basics_thirty",
      "type": "word",
      "text": "тридцять",
      "practiceType": "chooseTranslation"
    },
    {
      "id": "04_numbers_time_basics_forty",
      "type": "word",
      "text": "сорок",
      "practiceType": "chooseTranslation"
    },
    {
      "id": "04_numbers_time_basics_fifty",
      "type": "word",
      "text": "п'ятдесят",
      "practiceType": "chooseTranslation"
    },
    {
      "id": "04_numbers_time_basics_sixty",
      "type": "word",
      "text": "шістдесят",
      "practiceType": "chooseTranslation"
    },
    {
      "id": "04_numbers_time_basics_seventy",
      "type": "word",
      "text": "сімдесят",
      "practiceType": "chooseTranslation"
    },
    {
      "id": "04_numbers_time_basics_eighty",
      "type": "word",
      "text": "вісімдесят",
      "practiceType": "chooseTranslation"
    },
    {
      "id": "04_numbers_time_basics_ninety",
      "type": "word",
      "text": "дев'яносто",
      "practiceType": "chooseTranslation"
    },
    {
      "id": "04_numbers_time_basics_hundred",
      "type": "word",
      "text": "сто",
      "practiceType": "chooseTranslation"
    },
    {
      "id": "04_numbers_time_basics_two_hundred",
      "type": "word",
      "text": "двісті",
      "practiceType": "chooseTranslation"
    },
    {
      "id": "04_numbers_time_basics_three_hundred",
      "type": "word",
      "text": "триста",
      "practiceType": "chooseTranslation"
    },
    {
      "id": "04_numbers_time_basics_fifteen",
      "type": "word",
      "text": "п'ятнадцять",
      "practiceType": "chooseTranslation"
    },
    {
      "id": "04_numbers_time_basics_twenty_five",
      "type": "word",
      "text": "двадцять п'ять",
      "practiceType": "chooseTranslation"
    },
    {
      "id": "04_numbers_time_basics_forty_two",
      "type": "word",
      "text": "сорок два",
      "practiceType": "chooseTranslation"
    },
    {
      "id": "04_numbers_time_basics_seventy_eight",
      "type": "word",
      "text": "сімдесят вісім",
      "practiceType": "chooseTranslation"
    },
    {
      "id": "04_numbers_time_basics_one_hundred_twenty",
      "type": "word",
      "text": "сто двадцять",
      "practiceType": "chooseTranslation"
    },
    {
      "id": "04_numbers_time_basics_five_hundred",
      "type": "word",
      "text": "п'ятсот",
      "practiceType": "chooseTranslation"
    },
    {
      "id": "04_numbers_time_basics_eight_hundred_fifty",
      "type": "word",
      "text": "вісімсот п'ятдесят",
      "practiceType": "chooseTranslation"
    },
    {
      "id": "04_numbers_time_basics_thousand",
      "type": "word",
      "text": "тисяча",
      "practiceType": "chooseTranslation"
    },
    {
      "id": "04_numbers_time_basics_today",
      "type": "word",
      "text": "сьогодні",
      "practiceType": "chooseTranslation"
    },
    {
      "id": "04_numbers_time_basics_tomorrow",
      "type": "word",
      "text": "завтра",
      "practiceType": "chooseTranslation"
    },
    {
      "id": "04_numbers_time_basics_yesterday",
      "type": "word",
      "text": "вчора",
      "practiceType": "chooseTranslation"
    },
    {
      "id": "04_numbers_time_basics_now",
      "type": "word",
      "text": "зараз",
      "practiceType": "chooseTranslation"
    },
    {
      "id": "04_numbers_time_basics_what_time_is_it",
      "type": "sentence",
      "text": "Котра година?",
      "practiceType": "formulateSentense"
    },
    {
      "id": "04_numbers_time_basics_it_is_three_o_clock",
      "type": "sentence",
      "text": "Три години.",
      "practiceType": "formulateSentense"
    },
    {
      "id": "04_numbers_time_basics_it_is_half_past_two",
      "type": "sentence",
      "text": "Пів на третю.",
      "practiceType": "formulateSentense"
    },
    {
      "id": "04_numbers_time_basics_what_day_is_today",
      "type": "sentence",
      "text": "Який сьогодні день?",
      "practiceType": "formulateSentense"
    },
    {
      "id": "04_numbers_time_basics_today_is_monday",
      "type": "sentence",
      "text": "Сьогодні понеділок.",
      "practiceType": "formulateSentense"
    },
    {
      "id": "04_numbers_time_basics_see_you_tomorrow",
      "type": "sentence",
      "text": "До завтра.",
      "practiceType": "formulateSentense"
    },
    {
      "id": "04_numbers_time_basics_i_am_late",
      "type": "sentence",
      "text": "Я запізнююся.",
      "practiceType": "formulateSentense"
    },
    {
      "id": "04_numbers_time_basics_what_time_do_you_start",
      "type": "sentence",
      "text": "О котрій ви починаєте?",
      "practiceType": "formulateSentense"
    },
    {
      "id": "04_numbers_time_basics_it_is_time_to_go",
      "type": "sentence",
      "text": "Час іти.",
      "practiceType": "formulateSentense"
    },
    {
      "id": "04_numbers_time_basics_how_long_does_it_take",
      "type": "sentence",
      "text": "Скільки це займає?",
      "practiceType": "formulateSentense"
    }
  ]
}