{
  "id": "35_food_and_drinks_2",
  "title": "Їжа та напої (Part 2)",
  "emoji": "🍕",
  "language": "Ukrainian",
  "items": [
    {
      "id": "35_food_and_drinks_restaurant",
      "type": "word",
      "text": "ресторан",
      "practiceType": "chooseTranslation"
    },
    {
      "id": "35_food_and_drinks_menu",
      "type": "word",
      "text": "меню",
      "practiceType": "chooseTranslation"
    },
    {
      "id": "35_food_and_drinks_order",
      "type": "word",
      "text": "замовлення",
      "practiceType": "chooseTranslation"
    },
    {
      "id": "35_food_and_drinks_hungry",
      "type": "word",
      "text": "голодний",
      "practiceType": "chooseTranslation"
    },
    {
      "id": "35_food_and_drinks_thirsty",
      "type": "word",
      "text": "спитий",
      "practiceType": "chooseTranslation"
    },
    {
      "id": "35_food_and_drinks_can_i_see_the_menu",
      "type": "sentence",
      "text": "Можу я побачити меню?",
      "practiceType": "formulateSentense"
    },
    {
      "id": "35_food_and_drinks_i_want_to_order_pizza",
      "type": "sentence",
      "text": "Я хочу замовити піцу.",
      "practiceType": "formulateSentense"
    },
    {
      "id": "35_food_and_drinks_are_you_hungry",
      "type": "sentence",
      "text": "Ви голодні?",
      "practiceType": "formulateSentense"
    },
    {
      "id": "35_food_and_drinks_i_am_thirsty_can_i_have_water",
      "type": "sentence",
      "text": "Я хочу пити, можу я отримати воду?",
      "practiceType": "formulateSentense"
    },
    {
      "id": "35_food_and_drinks_this_food_tastes_delicious",
      "type": "sentence",
      "text": "Ця їжа смачна.",
      "practiceType": "formulateSentense"
    }
  ]
}