{
  "id": "hobbies",
  "emoji": "",
  "name": { 
    "en": "Hobbies", 
    "es": "Pasatiempos", 
    "he": "转" 
  },
  "description": { 
    "en": "Fun activities and hobbies", 
    "es": "Actividades divertidas y pasatiempos", 
    "he": "驻注转 转 转" 
  },
  "items": [
    { 
      "id": "reading", 
      "type": "word", 
      "text": { 
        "en": "reading", 
        "es": "lectura", 
        "he": "拽专" 
      } 
    },
    { 
      "id": "writing", 
      "type": "word", 
      "text": { 
        "en": "writing", 
        "es": "escritura", 
        "he": "转" 
      } 
    },
    { 
      "id": "drawing", 
      "type": "word", 
      "text": { 
        "en": "drawing", 
        "es": "dibujo", 
        "he": "爪专" 
      } 
    },
    { 
      "id": "painting", 
      "type": "word", 
      "text": { 
        "en": "painting", 
        "es": "pintura", 
        "he": "爪专" 
      } 
    },
    { 
      "id": "singing", 
      "type": "word", 
      "text": { 
        "en": "singing", 
        "es": "canto", 
        "he": "砖专" 
      } 
    },
    { 
      "id": "dancing", 
      "type": "word", 
      "text": { 
        "en": "dancing", 
        "es": "baile", 
        "he": "专拽" 
      } 
    },
    { 
      "id": "swimming", 
      "type": "word", 
      "text": { 
        "en": "swimming", 
        "es": "nataci贸n", 
        "he": "砖" 
      } 
    },
    { 
      "id": "running", 
      "type": "word", 
      "text": { 
        "en": "running", 
        "es": "correr", 
        "he": "专爪" 
      } 
    },
    { 
      "id": "cycling", 
      "type": "word", 
      "text": { 
        "en": "cycling", 
        "es": "ciclismo", 
        "he": "专 注 驻" 
      } 
    },
    { 
      "id": "cooking", 
      "type": "word", 
      "text": { 
        "en": "cooking", 
        "es": "cocina", 
        "he": "砖" 
      } 
    },
    { 
      "id": "baking", 
      "type": "word", 
      "text": { 
        "en": "baking", 
        "es": "hornear", 
        "he": "驻" 
      } 
    },
    { 
      "id": "gardening", 
      "type": "word", 
      "text": { 
        "en": "gardening", 
        "es": "jardiner铆a", 
        "he": "" 
      } 
    },
    { 
      "id": "photography", 
      "type": "word", 
      "text": { 
        "en": "photography", 
        "es": "fotograf铆a", 
        "he": "爪" 
      } 
    },
    { 
      "id": "fishing", 
      "type": "word", 
      "text": { 
        "en": "fishing", 
        "es": "pesca", 
        "he": "" 
      } 
    },
    { 
      "id": "hiking", 
      "type": "word", 
      "text": { 
        "en": "hiking", 
        "es": "senderismo", 
        "he": " 专" 
      } 
    },
    { 
      "id": "camping", 
      "type": "word", 
      "text": { 
        "en": "camping", 
        "es": "camping", 
        "he": "拽驻" 
      } 
    },
    { 
      "id": "knitting", 
      "type": "word", 
      "text": { 
        "en": "knitting", 
        "es": "tejer", 
        "he": "住专" 
      } 
    },
    { 
      "id": "sewing", 
      "type": "word", 
      "text": { 
        "en": "sewing", 
        "es": "costura", 
        "he": "转驻专" 
      } 
    },
    { 
      "id": "collecting", 
      "type": "word", 
      "text": { 
        "en": "collecting", 
        "es": "coleccionar", 
        "he": "住祝" 
      } 
    },
    { 
      "id": "puzzles", 
      "type": "word", 
      "text": { 
        "en": "puzzles", 
        "es": "rompecabezas", 
        "he": "驻" 
      } 
    }
  ]
}
