{
  "id": "06_food_drink_basics_1",
  "title": "Thức ăn và đồ uống cơ bản (Part 1)",
  "emoji": "🍎",
  "language": "Vietnamese",
  "items": [
    {
      "id": "06_food_drink_basics_water",
      "type": "word",
      "text": "nước",
      "practiceType": "chooseTranslation"
    },
    {
      "id": "06_food_drink_basics_coffee",
      "type": "word",
      "text": "cà phê",
      "practiceType": "chooseTranslation"
    },
    {
      "id": "06_food_drink_basics_tea",
      "type": "word",
      "text": "trà",
      "practiceType": "chooseTranslation"
    },
    {
      "id": "06_food_drink_basics_bread",
      "type": "word",
      "text": "bánh mì",
      "practiceType": "chooseTranslation"
    },
    {
      "id": "06_food_drink_basics_apple",
      "type": "word",
      "text": "táo",
      "practiceType": "chooseTranslation"
    },
    {
      "id": "06_food_drink_basics_i_would_like_water_please",
      "type": "sentence",
      "text": "Tôi muốn nước, xin vui lòng.",
      "practiceType": "formulateSentense"
    },
    {
      "id": "06_food_drink_basics_the_food_is_delicious",
      "type": "sentence",
      "text": "Thức ăn rất ngon.",
      "practiceType": "formulateSentense"
    },
    {
      "id": "06_food_drink_basics_i_am_allergic_to",
      "type": "sentence",
      "text": "Tôi bị dị ứng với …",
      "practiceType": "formulateSentense"
    },
    {
      "id": "06_food_drink_basics_no_sugar_please",
      "type": "sentence",
      "text": "Không đường, xin vui lòng.",
      "practiceType": "formulateSentense"
    },
    {
      "id": "06_food_drink_basics_do_you_have_vegetarian_food",
      "type": "sentence",
      "text": "Bạn có thức ăn chay không?",
      "practiceType": "formulateSentense"
    }
  ]
}