{
  "id": "38_animals_and_pets_2",
  "title": "Dieren en huisdieren (Part 2)",
  "emoji": "🐕",
  "language": "Dutch",
  "items": [
    {
      "id": "38_animals_and_pets_fish",
      "type": "word",
      "text": "vis",
      "practiceType": "chooseTranslation"
    },
    {
      "id": "38_animals_and_pets_horse",
      "type": "word",
      "text": "paard",
      "practiceType": "chooseTranslation"
    },
    {
      "id": "38_animals_and_pets_cow",
      "type": "word",
      "text": "koe",
      "practiceType": "chooseTranslation"
    },
    {
      "id": "38_animals_and_pets_chicken",
      "type": "word",
      "text": "kip",
      "practiceType": "chooseTranslation"
    },
    {
      "id": "38_animals_and_pets_pig",
      "type": "word",
      "text": "varken",
      "practiceType": "chooseTranslation"
    },
    {
      "id": "38_animals_and_pets_horses_are_beautiful_animals",
      "type": "sentence",
      "text": "Paarden zijn mooie dieren.",
      "practiceType": "formulateSentense"
    },
    {
      "id": "38_animals_and_pets_cows_give_us_milk",
      "type": "sentence",
      "text": "Koeien geven ons melk.",
      "practiceType": "formulateSentense"
    },
    {
      "id": "38_animals_and_pets_do_you_like_chicken",
      "type": "sentence",
      "text": "Vind je kip lekker?",
      "practiceType": "formulateSentense"
    },
    {
      "id": "38_animals_and_pets_pigs_are_very_intelligent",
      "type": "sentence",
      "text": "Varkens zijn heel intelligent.",
      "practiceType": "formulateSentense"
    },
    {
      "id": "38_animals_and_pets_what_is_your_favorite_animal",
      "type": "sentence",
      "text": "Wat is je favoriete dier?",
      "practiceType": "formulateSentense"
    }
  ]
}