{
  "id": "19_housing_utilities",
  "title": "Bostad och allmännyttiga tjänster",
  "emoji": "🏠",
  "language": "Swedish",
  "items": [
    {
      "id": "19_housing_utilities_apartment",
      "type": "word",
      "text": "lägenhet",
      "practiceType": "chooseTranslation"
    },
    {
      "id": "19_housing_utilities_room",
      "type": "word",
      "text": "rum",
      "practiceType": "chooseTranslation"
    },
    {
      "id": "19_housing_utilities_key",
      "type": "word",
      "text": "nyckel",
      "practiceType": "chooseTranslation"
    },
    {
      "id": "19_housing_utilities_electricity",
      "type": "word",
      "text": "el",
      "practiceType": "chooseTranslation"
    },
    {
      "id": "19_housing_utilities_water",
      "type": "word",
      "text": "vatten",
      "practiceType": "chooseTranslation"
    },
    {
      "id": "19_housing_utilities_house",
      "type": "word",
      "text": "hus",
      "practiceType": "chooseTranslation"
    },
    {
      "id": "19_housing_utilities_kitchen",
      "type": "word",
      "text": "kök",
      "practiceType": "chooseTranslation"
    },
    {
      "id": "19_housing_utilities_bathroom",
      "type": "word",
      "text": "badrum",
      "practiceType": "chooseTranslation"
    },
    {
      "id": "19_housing_utilities_heating",
      "type": "word",
      "text": "värme",
      "practiceType": "chooseTranslation"
    },
    {
      "id": "19_housing_utilities_rent",
      "type": "word",
      "text": "hyra",
      "practiceType": "chooseTranslation"
    },
    {
      "id": "19_housing_utilities_i_am_looking_for_an_apartment",
      "type": "sentence",
      "text": "Jag letar efter en lägenhet.",
      "practiceType": "formulateSentense"
    },
    {
      "id": "19_housing_utilities_the_key_does_not_work",
      "type": "sentence",
      "text": "Nyckeln fungerar inte.",
      "practiceType": "formulateSentense"
    },
    {
      "id": "19_housing_utilities_there_is_no_hot_water",
      "type": "sentence",
      "text": "Det finns inget varmt vatten.",
      "practiceType": "formulateSentense"
    },
    {
      "id": "19_housing_utilities_how_much_is_the_rent",
      "type": "sentence",
      "text": "Hur mycket är hyran?",
      "practiceType": "formulateSentense"
    },
    {
      "id": "19_housing_utilities_do_you_have_a_kitchen",
      "type": "sentence",
      "text": "Har du ett kök?",
      "practiceType": "formulateSentense"
    },
    {
      "id": "19_housing_utilities_the_heating_is_broken",
      "type": "sentence",
      "text": "Värmen är trasig.",
      "practiceType": "formulateSentense"
    },
    {
      "id": "19_housing_utilities_where_is_the_bathroom",
      "type": "sentence",
      "text": "Var är badrummet?",
      "practiceType": "formulateSentense"
    },
    {
      "id": "19_housing_utilities_is_electricity_included",
      "type": "sentence",
      "text": "Ingår el?",
      "practiceType": "formulateSentense"
    },
    {
      "id": "19_housing_utilities_can_i_see_the_house",
      "type": "sentence",
      "text": "Kan jag se huset?",
      "practiceType": "formulateSentense"
    },
    {
      "id": "19_housing_utilities_do_you_have_parking",
      "type": "sentence",
      "text": "Har du parkering?",
      "practiceType": "formulateSentense"
    }
  ]
}