{
  "id": "17_restaurant_1",
  "title": "In het restaurant (Part 1)",
  "emoji": "🍽️",
  "language": "Dutch",
  "items": [
    {
      "id": "17_restaurant_menu",
      "type": "word",
      "text": "menu",
      "practiceType": "chooseTranslation"
    },
    {
      "id": "17_restaurant_table",
      "type": "word",
      "text": "tafel",
      "practiceType": "chooseTranslation"
    },
    {
      "id": "17_restaurant_bill",
      "type": "word",
      "text": "rekening",
      "practiceType": "chooseTranslation"
    },
    {
      "id": "17_restaurant_waiter",
      "type": "word",
      "text": "ober",
      "practiceType": "chooseTranslation"
    },
    {
      "id": "17_restaurant_food",
      "type": "word",
      "text": "eten",
      "practiceType": "chooseTranslation"
    },
    {
      "id": "17_restaurant_a_table_for_two_please",
      "type": "sentence",
      "text": "Een tafel voor twee, alsjeblieft.",
      "practiceType": "formulateSentense"
    },
    {
      "id": "17_restaurant_could_we_have_the_menu",
      "type": "sentence",
      "text": "Kunnen we het menu hebben?",
      "practiceType": "formulateSentense"
    },
    {
      "id": "17_restaurant_the_bill_please",
      "type": "sentence",
      "text": "De rekening, alsjeblieft.",
      "practiceType": "formulateSentense"
    },
    {
      "id": "17_restaurant_do_you_have_vegetarian_options",
      "type": "sentence",
      "text": "Heb je vegetarische opties?",
      "practiceType": "formulateSentense"
    },
    {
      "id": "17_restaurant_what_do_you_recommend",
      "type": "sentence",
      "text": "Wat raad je aan?",
      "practiceType": "formulateSentense"
    }
  ]
}