{
  "id": "38_animals_and_pets_2",
  "title": "Animals & Pets (Part 2)",
  "emoji": "🐕",
  "language": "German",
  "items": [
    {
      "id": "38_animals_and_pets_fish",
      "type": "word",
      "text": "Fisch",
      "practiceType": "chooseTranslation"
    },
    {
      "id": "38_animals_and_pets_horse",
      "type": "word",
      "text": "Pferd",
      "practiceType": "chooseTranslation"
    },
    {
      "id": "38_animals_and_pets_cow",
      "type": "word",
      "text": "Kuh",
      "practiceType": "chooseTranslation"
    },
    {
      "id": "38_animals_and_pets_pig",
      "type": "word",
      "text": "Schwein",
      "practiceType": "chooseTranslation"
    },
    {
      "id": "38_animals_and_pets_chicken",
      "type": "word",
      "text": "Huhn",
      "practiceType": "chooseTranslation"
    },
    {
      "id": "38_animals_and_pets_animals_are_amazing",
      "type": "sentence",
      "text": "Tiere sind erstaunlich.",
      "practiceType": "formulateSentense"
    },
    {
      "id": "38_animals_and_pets_my_cat_likes_to_sleep",
      "type": "sentence",
      "text": "Meine Katze schläft gerne.",
      "practiceType": "formulateSentense"
    },
    {
      "id": "38_animals_and_pets_do_you_like_dogs",
      "type": "sentence",
      "text": "Mögen Sie Hunde?",
      "practiceType": "formulateSentense"
    },
    {
      "id": "38_animals_and_pets_pets_are_great_companions",
      "type": "sentence",
      "text": "Haustiere sind tolle Begleiter.",
      "practiceType": "formulateSentense"
    },
    {
      "id": "38_animals_and_pets_animals_are_our_friends",
      "type": "sentence",
      "text": "Tiere sind unsere Freunde.",
      "practiceType": "formulateSentense"
    }
  ]
}